IMcore/IMTips.py
IMcore/IMVisualConf.py
IMcore/IMencode.py
IMcore/IMextension.py
IMcore/IMmanager.py
IMcore/IMplots.py
IMcore/IMprocessor.py
IMcore/IMsets.py
IMcore/IMtrans.py
IMcore/IMutils.py
IMcore/IMvisual.py
IMcore/IMwidget.py
IMcore/VisualConf.py
IMcore/VisualSet.yaml
IMcore/__init__.py
IMcore/simkai.ttf
IMcore/IMlibs/__init__.py
IMcore/IMlibs/py310/alpine_aarch64/pyarmor_runtime.so
IMcore/IMlibs/py310/alpine_x86_64/pyarmor_runtime.so
IMcore/IMlibs/py310/android_aarch64/pyarmor_runtime.so
IMcore/IMlibs/py310/android_armv7/pyarmor_runtime.so
IMcore/IMlibs/py310/android_x86/pyarmor_runtime.so
IMcore/IMlibs/py310/android_x86_64/pyarmor_runtime.so
IMcore/IMlibs/py310/darwin_aarch64/pyarmor_runtime.so
IMcore/IMlibs/py310/darwin_arm64/pyarmor_runtime.so
IMcore/IMlibs/py310/darwin_x86_64/pyarmor_runtime.so
IMcore/IMlibs/py310/freebsd_x86_64/pyarmor_runtime.so
IMcore/IMlibs/py310/linux_aarch64/pyarmor_runtime.so
IMcore/IMlibs/py310/linux_armv7/pyarmor_runtime.so
IMcore/IMlibs/py310/linux_x86/pyarmor_runtime.so
IMcore/IMlibs/py310/linux_x86_64/pyarmor_runtime.so
IMcore/IMlibs/py310/windows_x86/pyarmor_runtime.pyd
IMcore/IMlibs/py310/windows_x86_64/pyarmor_runtime.pyd
IMcore/IMlibs/py311/alpine_aarch64/pyarmor_runtime.so
IMcore/IMlibs/py311/alpine_x86_64/pyarmor_runtime.so
IMcore/IMlibs/py311/android_aarch64/pyarmor_runtime.so
IMcore/IMlibs/py311/android_armv7/pyarmor_runtime.so
IMcore/IMlibs/py311/android_x86/pyarmor_runtime.so
IMcore/IMlibs/py311/android_x86_64/pyarmor_runtime.so
IMcore/IMlibs/py311/darwin_aarch64/pyarmor_runtime.so
IMcore/IMlibs/py311/darwin_arm64/pyarmor_runtime.so
IMcore/IMlibs/py311/darwin_x86_64/pyarmor_runtime.so
IMcore/IMlibs/py311/freebsd_x86_64/pyarmor_runtime.so
IMcore/IMlibs/py311/linux_aarch64/pyarmor_runtime.so
IMcore/IMlibs/py311/linux_armv7/pyarmor_runtime.so
IMcore/IMlibs/py311/linux_x86/pyarmor_runtime.so
IMcore/IMlibs/py311/linux_x86_64/pyarmor_runtime.so
IMcore/IMlibs/py311/windows_x86/pyarmor_runtime.pyd
IMcore-0.3.1.dist-info/METADATA
IMcore-0.3.1.dist-info/WHEEL
IMcore-0.3.1.dist-info/top_level.txt
IMcore-0.3.1.dist-info/RECORD
